problemtools/__init__.py
problemtools/_version.py
problemtools/config.py
problemtools/formatversion.py
problemtools/languages.py
problemtools/md2html.py
problemtools/metadata.py
problemtools/problem2html.py
problemtools/problem2pdf.py
problemtools/py.typed
problemtools/statement_util.py
problemtools/template.py
problemtools/tex2html.py
problemtools/update_from_old_problemformat.py
problemtools/verifyproblem.py
problemtools/ProblemPlasTeX/ProblemsetMacros.py
problemtools/ProblemPlasTeX/__init__.py
problemtools/ProblemPlasTeX/graphicx.py
problemtools/ProblemPlasTeX/import.py
problemtools/ProblemPlasTeX/listingsutf8.py
problemtools/ProblemPlasTeX/ulem.py
problemtools/config/languages.yaml
problemtools/config/problem.yaml
problemtools/config/testdata.yaml
problemtools/run/__init__.py
problemtools/run/buildrun.py
problemtools/run/checktestdata.py
problemtools/run/errors.py
problemtools/run/executable.py
problemtools/run/limit.py
problemtools/run/program.py
problemtools/run/rutil.py
problemtools/run/source.py
problemtools/run/tools.py
problemtools/run/viva.py
problemtools/support/checktestdata
problemtools/support/default_grader
problemtools/support/default_validator
problemtools/support/interactive
problemtools/support/viva.jar
problemtools/support/viva.sh
problemtools/templates/html/Accents.zpts
problemtools/templates/html/Alignment.zpts
problemtools/templates/html/Arrays.zpts
problemtools/templates/html/Bibliography.zpts
problemtools/templates/html/Boxes.zpts
problemtools/templates/html/Breaking.zpts
problemtools/templates/html/Crossref.zpts
problemtools/templates/html/Floats.zpts
problemtools/templates/html/FontSelection.zpts
problemtools/templates/html/Footnotes.zpts
problemtools/templates/html/Index.zpts
problemtools/templates/html/Lists.zpts
problemtools/templates/html/Math.zpts
problemtools/templates/html/Misc.zpts
problemtools/templates/html/Pictures.zpts
problemtools/templates/html/Primitives.zpts
problemtools-1.20250606.dist-info/METADATA
problemtools-1.20250606.dist-info/WHEEL
problemtools-1.20250606.dist-info/entry_points.txt
problemtools-1.20250606.dist-info/top_level.txt
problemtools-1.20250606.dist-info/RECORD
problemtools-1.20250606.dist-info/licenses/LICENSE
