Metadata-Version: 2.4
Name: problemtools
Version: 1.20250606
Summary: Kattis Problem Tools
Author-email: Kattis AB <contact@kattis.com>
License-Expression: MIT
Project-URL: Repository, https://github.com/Kattis/problemtools
Project-URL: Homepage, https://www.kattis.com
Project-URL: Documentation, https://www.kattis.com/problem-package-format/
Project-URL: Issues, https://github.com/Kattis/problemtools/issues/
Keywords: kattis,problemtools,icpc,clics
Requires-Python: >=3.11
License-File: LICENSE
Requires-Dist: colorlog
Requires-Dist: nh3
Requires-Dist: PyYAML
Requires-Dist: plasTeX>=3.0
Requires-Dist: pydantic>=2.11
Dynamic: license-file
